ONUR_Voice_Assistant
