Metadata-Version: 2.1
Name: ONUR-Voice-Assistant
Version: 0.1.3
Summary: A modular and expandable voice assistant
Home-page: https://github.com/onuratakan/say_me_something
Author: Onur Atakan ULUSOY
Author-email: atadogan06@gmail.com
License: MIT
Platform: UNKNOWN
Requires-Python: >= 3, < 3.7
License-File: LICENSE
